spy/__init__.py
spy/spy.py
fsspy-1.0.2.dist-info/LICENSE
fsspy-1.0.2.dist-info/METADATA
fsspy-1.0.2.dist-info/WHEEL
fsspy-1.0.2.dist-info/entry_points.txt
fsspy-1.0.2.dist-info/top_level.txt
fsspy-1.0.2.dist-info/RECORD
