Metadata-Version: 2.1
Name: fsspy
Version: 1.0.2
Summary: Filesystem events watcher
Home-page: https://github.com/clobrano/spy
Author: Carlo Lobrano
Author-email: <c.lobrano@gmail.com>
License: UNKNOWN
Platform: UNKNOWN
Requires-Python: >=3.6
License-File: LICENSE
Requires-Dist: watchdog
